[
  {
    "municipio": "Campos Sales",
    "data_pdf": "02 de Janeiro de 2023",
    "num_avisos_licitacao": 0
  },
  {
    "municipio": "Campos Sales",
    "data_pdf": "03 de Janeiro de 2023",
    "num_avisos_licitacao": 0
  },
  {
    "municipio": "Campos Sales",
    "data_pdf": "04 de Janeiro de 2023",
    "num_avisos_licitacao": 0
  },
  {
    "municipio": "Campos Sales",
    "data_pdf": "05 de Janeiro de 2023",
    "num_avisos_licitacao": 0
  },
  {
    "municipio": "Campos Sales",
    "data_pdf": "06 de Janeiro de 2023",
    "num_avisos_licitacao": 0
  }
]