[
  {
    "municipio": "milagres",
    "month": "Janeiro",
    "sum_num_avisos_licitacao": 4
  },
  {
    "municipio": "milagres",
    "month": "Fevereiro",
    "sum_num_avisos_licitacao": 0
  },
  {
    "municipio": "milagres",
    "month": "Março",
    "sum_num_avisos_licitacao": 10
  },
  {
    "municipio": "milagres",
    "month": "Abril",
    "sum_num_avisos_licitacao": 5
  },
  {
    "municipio": "milagres",
    "month": "Maio",
    "sum_num_avisos_licitacao": 0
  },
  {
    "municipio": "milagres",
    "month": "Junho",
    "sum_num_avisos_licitacao": 6
  },
  {
    "municipio": "milagres",
    "month": "Julho",
    "sum_num_avisos_licitacao": 0
  },
  {
    "municipio": "milagres",
    "month": "Agosto",
    "sum_num_avisos_licitacao": 0
  },
  {
    "municipio": "milagres",
    "month": "Setembro",
    "sum_num_avisos_licitacao": 2
  },
  {
    "municipio": "milagres",
    "month": "Outubro",
    "sum_num_avisos_licitacao": 2
  },
  {
    "municipio": "milagres",
    "month": "Novembro",
    "sum_num_avisos_licitacao": 2
  }
]